Workbook

Sheet Summary
A1: RENTAL ARREARS AGEING REPORT
A2: As at 30 September 2026 - Finance & Arrears
A4: Bucket (days) | B4: No. of tenancies | C4: Amount (incl GST) | D4: % of total
A5: 0-30 | B5: =COUNTIF(Data!L2:L136,"0-30") | C5: =SUMIF(Data!L2:L136,"0-30",Data!J2:J136) | D5: =C5/C9
A6: 31-60 | B6: =COUNTIF(Data!L2:L136,"31-60") | C6: =SUMIF(Data!L2:L136,"31-60",Data!J2:J136) | D6: =C6/C9
A7: 61-90 | B7: =COUNTIF(Data!L2:L136,"61-90") | C7: =SUMIF(Data!L2:L136,"61-90",Data!J2:J136) | D7: =C7/C9
A8: >90 | B8: =COUNTIF(Data!L2:L136,">90") | C8: =SUMIF(Data!L2:L136,">90",Data!J2:J136) | D8: =C8/C9
A9: Total | B9: =SUM(B5:B8) | C9: =SUM(C5:C8)
A11: Town | B11: No. of tenancies | C11: Amount (incl GST) | D11: > 3 months' rent
A12: Bayshore Vale | B12: =COUNTIF(Data!E2:E136,A12) | C12: =SUMIF(Data!E2:E136,A12,Data!J2:J136) | D12: =COUNTIFS(Data!E2:E136,A12,Data!M2:M136,"YES")
A13: Cendana | B13: =COUNTIF(Data!E2:E136,A13) | C13: =SUMIF(Data!E2:E136,A13,Data!J2:J136) | D13: =COUNTIFS(Data!E2:E136,A13,Data!M2:M136,"YES")
A14: Kebun Raya | B14: =COUNTIF(Data!E2:E136,A14) | C14: =SUMIF(Data!E2:E136,A14,Data!J2:J136) | D14: =COUNTIFS(Data!E2:E136,A14,Data!M2:M136,"YES")
A15: Rimba Heights | B15: =COUNTIF(Data!E2:E136,A15) | C15: =SUMIF(Data!E2:E136,A15,Data!J2:J136) | D15: =COUNTIFS(Data!E2:E136,A15,Data!M2:M136,"YES")
A16: Sungai Tinggi | B16: =COUNTIF(Data!E2:E136,A16) | C16: =SUMIF(Data!E2:E136,A16,Data!J2:J136) | D16: =COUNTIFS(Data!E2:E136,A16,Data!M2:M136,"YES")
A17: Pasir Indah | B17: =COUNTIF(Data!E2:E136,A17) | C17: =SUMIF(Data!E2:E136,A17,Data!J2:J136) | D17: =COUNTIFS(Data!E2:E136,A17,Data!M2:M136,"YES")
A19: Notes: Termination threshold = arrears > 3 months' rent incl. GST (PLG-POL-003 v2.0). Interest not included.
A20: Static check: 135 tenancies in arrears, total S$962,688.00.

Sheet Data
A1: Tenancy ID | B1: Tenant ID | C1: Tenant name | D1: Unit ID | E1: Town | F1: Monthly rent | G1: Unpaid invoices | H1: Oldest due date | I1: Days overdue | J1: Arrears (incl GST) | K1: Months of rent | L1: Bucket | M1: > 3 months?
A2: TA-2024-00319 | B2: T-10766 | C2: Barakah Boba Bar Pte Ltd | D2: U-PI614-01-06 | E2: Pasir Indah | F2: 4330 | G2: 7 | H2: 46082 | I2: 213 | J2: 33037.9 | K2: =J2/(F2*1.09) | L2: >90 | M2: =IF(K2>3,"YES","")
A3: TA-2024-00185 | B3: T-10549 | C3: Hup Seng Learning Centre Pte Ltd | D3: U-KR335-01-03 | E3: Kebun Raya | F3: 3350 | G3: 7 | H3: 46082 | I3: 213 | J3: 25560.5 | K3: =J3/(F3*1.09) | L3: >90 | M3: =IF(K3>3,"YES","")
A4: TA-2024-00542 | B4: T-11108 | C4: Golden Leaf Minimart Pte Ltd | D4: U-BV214-01-32 | E4: Bayshore Vale | F4: 5200 | G4: 4 | H4: 46174 | I4: 121 | J4: 22672 | K4: =J4/(F4*1.09) | L4: >90 | M4: =IF(K4>3,"YES","")
A5: TA-2025-00548 | B5: T-12418 | C5: Little Sprouts Family Clinic | D5: U-PI627-02-23 | E5: Pasir Indah | F5: 3200 | G5: 6 | H5: 46113 | I5: 182 | J5: 20928 | K5: =J5/(F5*1.09) | L5: >90 | M5: =IF(K5>3,"YES","")
A6: TA-2025-00106 | B6: T-11671 | C6: Smart Kids Bookstore | D6: U-KR368-01-10 | E6: Kebun Raya | F6: 3680 | G6: 5 | H6: 46143 | I6: 152 | J6: 20056 | K6: =J6/(F6*1.09) | L6: >90 | M6: =IF(K6>3,"YES","")
A7: TA-2026-00054 | B7: T-12858 | C7: Treasure Mart Pte Ltd | D7: U-RH484-01-03 | E7: Rimba Heights | F7: 2560 | G7: 7 | H7: 46082 | I7: 213 | J7: 19532.8 | K7: =J7/(F7*1.09) | L7: >90 | M7: =IF(K7>3,"YES","")
A8: TA-2025-00623 | B8: T-12533 | C8: Sejahtera Minimart Pte Ltd | D8: U-RH425-01-01 | E8: Rimba Heights | F8: 3430 | G8: 5 | H8: 46143 | I8: 152 | J8: 18693.5 | K8: =J8/(F8*1.09) | L8: >90 | M8: =IF(K8>3,"YES","")
A9: TA-2025-00669 | B9: T-12604 | C9: Thye Hin Mart | D9: U-KR371-01-08 | E9: Kebun Raya | F9: 3350 | G9: 5 | H9: 46143 | I9: 152 | J9: 18257.5 | K9: =J9/(F9*1.09) | L9: >90 | M9: =IF(K9>3,"YES","")
A10: TA-2024-00228 | B10: T-10613 | C10: Cosy Hair Studio | D10: U-CD133-01-08 | E10: Cendana | F10: 2640 | G10: 6 | H10: 46113 | I10: 182 | J10: 17265.6 | K10: =J10/(F10*1.09) | L10: >90 | M10: =IF(K10>3,"YES","")
A11: TA-2024-00612 | B11: T-11223 | C11: Jade Garden Accounting Services Pte Ltd | D11: U-BV231-02-10 | E11: Bayshore Vale | F11: 3130 | G11: 5 | H11: 46143 | I11: 152 | J11: 17058.5 | K11: =J11/(F11*1.09) | L11: >90 | M11: =IF(K11>3,"YES","")
A12: TA-2025-00422 | B12: T-12213 | C12: Old Town Money Changer | D12: U-KR385-01-06 | E12: Kebun Raya | F12: 3830 | G12: 4 | H12: 46174 | I12: 121 | J12: 16698.8 | K12: =J12/(F12*1.09) | L12: >90 | M12: =IF(K12>3,"YES","")
A13: TA-2025-00213 | B13: T-11869 | C13: Old Town Pharmacy | D13: U-KR353-01-07 | E13: Kebun Raya | F13: 3020 | G13: 5 | H13: 46143 | I13: 152 | J13: 16459 | K13: =J13/(F13*1.09) | L13: >90 | M13: =IF(K13>3,"YES","")
... A136: TA-2026-00608 | B136: T-13722 | C136: Hock Lee Flowers & Gifts Pte Ltd | D136: U-ST512-01-26 | E136: Sungai Tinggi | F136: 900 | G136: 1 | H136: 46266 | I136: 29 | J136: 981 | K136: =J136/(F136*1.09) | L136: 0-30 | M136: =IF(K136>3,"YES","")

Sheet Unpaid Invoices
A1: Invoice ID | B1: Tenancy ID | C1: Period | D1: Due date | E1: Total (incl GST)
A2: INV-2603-000249 | B2: TA-2024-00185 | C2: 2026-03 | D2: 46082 | E2: 3651.5
A3: INV-2603-000344 | B3: TA-2024-00319 | C3: 2026-03 | D3: 46082 | E3: 4719.7
A4: INV-2603-001217 | B4: TA-2026-00054 | C4: 2026-03 | D4: 46082 | E4: 2790.4
A5: INV-2604-000249 | B5: TA-2024-00185 | C5: 2026-04 | D5: 46113 | E5: 3651.5
A6: INV-2604-000280 | B6: TA-2024-00228 | C6: 2026-04 | D6: 46113 | E6: 2877.6
A7: INV-2604-000344 | B7: TA-2024-00319 | C7: 2026-04 | D7: 46113 | E7: 4719.7
A8: INV-2604-001041 | B8: TA-2025-00548 | C8: 2026-04 | D8: 46113 | E8: 3488
A9: INV-2604-001217 | B9: TA-2026-00054 | C9: 2026-04 | D9: 46113 | E9: 2790.4
A10: INV-2604-001461 | B10: TA-2023-00537 | C10: 2026-04 | D10: 46113 | E10: 937.4
A11: INV-2605-000031 | B11: TA-2023-00045 | C11: 2026-05 | D11: 46143 | E11: 981
A12: INV-2605-000249 | B12: TA-2024-00185 | C12: 2026-05 | D12: 46143 | E12: 3651.5
A13: INV-2605-000280 | B13: TA-2024-00228 | C13: 2026-05 | D13: 46143 | E13: 2877.6
... A269: INV-2609-001584 | B269: TA-2026-00608 | C269: 2026-09 | D269: 46266 | E269: 981
